{
  "display": {
    "icon": {
      "item": "chaosmod:custom_log"
    },
    "title": {
      "text": "ChaosMod",
      "color": "blue",
      "bold": true,
      "italic": false,
      "hoverEvent": {
        "action": "show_text"
      }
    },
    "description": "Harvest custom logs",
    "frame": "task",
    "background": "minecraft:textures/gui/advancements/backgrounds/adventure.png",
    "show_toast": true,
    "announce_to_chat": true,
    "hidden": false
  },
  "criteria": {
    "got_wheat": {
      "trigger": "minecraft:inventory_changed",
      "conditions": {
        "items": [
          {
              "item": "chaosmod:custom_log"
          }
        ]
      }
    }
  },
  "requirements": []
}